texere/__init__.py
texere/edges.py
texere/purge.py
texere-1.0.2.dist-info/LICENSE
texere-1.0.2.dist-info/METADATA
texere-1.0.2.dist-info/WHEEL
texere-1.0.2.dist-info/top_level.txt
texere-1.0.2.dist-info/RECORD
